{
  "title": "Tuesday night 30 October 2018 on ABC",
  "special": "Alt-Rock Special on Rage",
  "timeslot": "night",
  "date": "2018-10-30",
  "url": "https://www.abc.net.au/rage/playlist/tuesday-night-30-october-2018-on-abc/10442832",
  "tracks": [
    {
      "artist": "SONIC YOUTH",
      "song": "Teenage Riot",
      "label": "Universal (MCA)",
      "timeslot": "01:30:00"
    },
    {
      "artist": "SONIC YOUTH",
      "song": "100%",
      "label": "Universal (MCA)",
      "timeslot": "01:30:00"
    },
    {
      "artist": "SEBADOH",
      "song": "Rebound",
      "label": "Shock",
      "timeslot": "01:30:00"
    },
    {
      "artist": "PAVEMENT",
      "song": "Father To A Sister Of Thought",
      "label": "Shock",
      "timeslot": "01:30:00"
    },
    {
      "artist": "ARCHERS OF LOAF",
      "song": "Web In Front",
      "label": "Shock",
      "timeslot": "02:00:00"
    },
    {
      "artist": "THE MARK OF CAIN",
      "song": "Interloper",
      "label": "BMG",
      "timeslot": "02:00:00"
    },
    {
      "artist": "MY BLOODY VALENTINE",
      "song": "You Made Me Realize",
      "label": "Shock",
      "timeslot": "02:00:00"
    },
    {
      "artist": "DINOSAUR JNR",
      "song": "Going Home",
      "label": "Warner",
      "timeslot": "02:00:00"
    },
    {
      "artist": "VERUCA SALT",
      "song": "Number One Blind",
      "label": "Shock",
      "timeslot": "02:00:00"
    },
    {
      "artist": "GUMBALL",
      "song": "Revolution On The Rocks",
      "label": "Sony",
      "timeslot": "02:00:00"
    },
    {
      "artist": "SUPERCHUNK",
      "song": "Fishing",
      "label": "Shock",
      "timeslot": "02:00:00"
    },
    {
      "artist": "THE CLOUDS",
      "song": "Hieronymus",
      "label": "Polydor",
      "timeslot": "02:00:00"
    },
    {
      "artist": "THE PRESIDENTS OF THE USA",
      "song": "Dune Buggy",
      "label": "Sony",
      "timeslot": "02:00:00"
    },
    {
      "artist": "GUIDED BY VOICES",
      "song": "Motor Away/Auditorium",
      "label": "Shock",
      "timeslot": "02:30:00"
    },
    {
      "artist": "WEEN",
      "song": "Can't Put My Finger On It",
      "label": "Mushroom",
      "timeslot": "02:30:00"
    },
    {
      "artist": "ARAB STRAP",
      "song": "Cherubs",
      "label": "Fest/Mush",
      "timeslot": "02:30:00"
    },
    {
      "artist": "THE JESUS LIZARD",
      "song": "Puss",
      "label": "Shock",
      "timeslot": "02:30:00"
    },
    {
      "artist": "BUTTHOLE SURFERS",
      "song": "Who Was In My Room Last Night?",
      "label": "EMI",
      "timeslot": "02:30:00"
    },
    {
      "artist": "ROYAL TRUX",
      "song": "Liar",
      "label": "Domino",
      "timeslot": "02:30:00"
    },
    {
      "artist": "MERCURY REV",
      "song": "Goddess On A Hiway",
      "label": "V2",
      "timeslot": "02:30:00"
    },
    {
      "artist": "HUGGY BEAR",
      "song": "Pansy Twist",
      "label": "Murmur",
      "timeslot": "02:30:00"
    },
    {
      "artist": "BIG BLACK",
      "song": "Fish Fry",
      "label": "Shock",
      "timeslot": "02:30:00"
    },
    {
      "artist": "LIZ PHAIR",
      "song": "Supernova",
      "label": "Warner",
      "timeslot": "03:00:00"
    },
    {
      "artist": "THE BREEDERS",
      "song": "Divine Hammer",
      "label": "Shock",
      "timeslot": "03:00:00"
    },
    {
      "artist": "SMASHING PUMPKINS",
      "song": "Rhinoceros",
      "label": "Virgin",
      "timeslot": "03:00:00"
    },
    {
      "artist": "RIDE",
      "song": "Vapour Trail",
      "label": "Warner",
      "timeslot": "03:00:00"
    },
    {
      "artist": "MOGWAI",
      "song": "Xmas Steps",
      "label": "Independent",
      "timeslot": "03:00:00"
    },
    {
      "artist": "BOREDOMS",
      "song": "Newsun",
      "label": "Independent",
      "timeslot": "03:00:00"
    },
    {
      "artist": "MUDHONEY",
      "song": "This Gift",
      "label": "Warner",
      "timeslot": "03:30:00"
    },
    {
      "artist": "PJ HARVEY",
      "song": "Dress",
      "label": "Shock",
      "timeslot": "03:30:00"
    },
    {
      "artist": "AMMONIA",
      "song": "Drugs",
      "label": "Sony",
      "timeslot": "03:30:00"
    },
    {
      "artist": "MAZZY STAR",
      "song": "Halah",
      "label": "EMI",
      "timeslot": "03:30:00"
    },
    {
      "artist": "THE REPLACEMENTS",
      "song": "Bastards Of Young",
      "label": "Warner",
      "timeslot": "03:30:00"
    },
    {
      "artist": "THE CELIBATE RIFLES",
      "song": "Tick, Tock",
      "label": "EMI",
      "timeslot": "03:30:00"
    },
    {
      "artist": "LUBRICATED GOAT",
      "song": "In The Raw",
      "label": "Independent",
      "timeslot": "03:30:00"
    },
    {
      "artist": "TEENAGE FANCLUB",
      "song": "Ain't That Enough",
      "label": "Sony",
      "timeslot": "03:30:00"
    },
    {
      "artist": "YOU AM I",
      "song": "Adam's Ribs",
      "label": "BMG",
      "timeslot": "04:00:00"
    },
    {
      "artist": "R.E.M.",
      "song": "Orange Crush",
      "label": "Warner",
      "timeslot": "04:00:00"
    },
    {
      "artist": "THROWING MUSES",
      "song": "Dizzy",
      "label": "Shock",
      "timeslot": "04:00:00"
    },
    {
      "artist": "THE AFGHAN WHIGS",
      "song": "Gentlemen",
      "label": "Warner",
      "timeslot": "04:00:00"
    },
    {
      "artist": "THE SUNDAYS",
      "song": "Here's Where The Story Ends",
      "label": "Festival",
      "timeslot": "04:00:00"
    },
    {
      "artist": "JON SPENCER BLUES EXPLOSION - LIVE ON RECOVERY",
      "song": "2 Kindsa Love",
      "label": "Au-Go-Go",
      "timeslot": "04:00:00"
    },
    {
      "artist": "L7",
      "song": "Stuck Here Again",
      "label": "Mushroom",
      "timeslot": "04:00:00"
    },
    {
      "artist": "SUNNY DAY REAL ESTATE",
      "song": "Seven",
      "label": "Shock",
      "timeslot": "04:00:00"
    },
    {
      "artist": "SONIC YOUTH",
      "song": "Sugar Kane",
      "label": "Universal (MCA)",
      "timeslot": "04:30:00"
    },
    {
      "artist": "SONIC YOUTH",
      "song": "Superstar",
      "label": "Polydor",
      "timeslot": "04:30:00"
    }
  ]
}