{
  "title": "Sunday night 27th August 2017 on ABC",
  "special": null,
  "timeslot": "night",
  "date": "2017-08-27",
  "url": "https://www.abc.net.au/rage/playlist/sunday-night-27th-august-2017-on-abc/9645384",
  "tracks": [
    {
      "artist": "GORDI",
      "song": "Bitter End",
      "label": "Liberation",
      "timeslot": "00:30:00"
    },
    {
      "artist": "JESS LOCKE",
      "song": "Universe",
      "label": "Remote Control",
      "timeslot": "00:30:00"
    },
    {
      "artist": "LCD SOUNDSYSTEM",
      "song": "Tonite",
      "label": "Columbia",
      "timeslot": "01:00:00"
    },
    {
      "artist": "THE JEZABELS",
      "song": "The Others",
      "label": "Independent",
      "timeslot": "01:00:00"
    },
    {
      "artist": "DZ DEATHRAYS",
      "song": "Shred For Summer",
      "label": "I OH YOU",
      "timeslot": "01:00:00"
    },
    {
      "artist": "ALEX CAMERON ft. ANGEL OLSEN",
      "song": "Stranger's Kiss",
      "label": "Secretly Canadian",
      "timeslot": "01:00:00"
    },
    {
      "artist": "FATHER JOHN MISTY",
      "song": "Things It Would Have Been Helpful To Know Before The Revolution",
      "label": "Inertia",
      "timeslot": "01:00:00"
    },
    {
      "artist": "LAWRENCE ROTHMAN",
      "song": "Wolves Still Cry",
      "label": "Downtown Records",
      "timeslot": "01:00:00"
    },
    {
      "artist": "MALLRAT",
      "song": "Uninvited",
      "label": "Universal",
      "timeslot": "01:00:00"
    },
    {
      "artist": "HERCULES and LOVE AFFAIR",
      "song": "Omnion",
      "label": "DFA",
      "timeslot": "01:30:00"
    },
    {
      "artist": "THE HARPOONS",
      "song": "Do You Want My love",
      "label": "Independent",
      "timeslot": "01:30:00"
    },
    {
      "artist": "GORILLAZ",
      "song": "Strobelite",
      "label": "Parlophone",
      "timeslot": "01:30:00"
    },
    {
      "artist": "PRINCIPAL",
      "song": "His Knife Collection",
      "label": "Spunk",
      "timeslot": "01:30:00"
    },
    {
      "artist": "DJ SHADOW ft STEVEN PRICE",
      "song": "Corridors",
      "label": "Sony",
      "timeslot": "01:30:00"
    },
    {
      "artist": "BANOFFEE",
      "song": "Ripe",
      "label": "Remote Control",
      "timeslot": "01:30:00"
    },
    {
      "artist": "CONFIDENCE MAN",
      "song": "Boyfriend (Repeat)",
      "label": "Amplifire",
      "timeslot": "01:30:00"
    },
    {
      "artist": "LORDE",
      "song": "Perfect Places",
      "label": "Nuclear Blast",
      "timeslot": "01:30:00"
    },
    {
      "artist": "THE PREATURES",
      "song": "Yanada",
      "label": "Universal",
      "timeslot": "02:00:00"
    },
    {
      "artist": "SCHOOL DAMAGE",
      "song": "Gasbagging",
      "label": "Chapter Music",
      "timeslot": "02:00:00"
    },
    {
      "artist": "WALKER and ROYCE FT. DANCES WITH WHITE GIRLS",
      "song": "Take Me To Your Leader",
      "label": "Etc Etc",
      "timeslot": "02:00:00"
    },
    {
      "artist": "KND",
      "song": "Cut Me",
      "label": "Independent",
      "timeslot": "02:00:00"
    },
    {
      "artist": "OKENYO",
      "song": "Woman's World",
      "label": "Elefant Traks",
      "timeslot": "02:00:00"
    },
    {
      "artist": "LUNICE ft. DENZEL CURRY, JK THE REAPER AND NELL",
      "song": "Distrust",
      "label": "Inertia",
      "timeslot": "02:00:00"
    },
    {
      "artist": "MARK HARDING",
      "song": "Thorn In Your Side",
      "label": "Independent",
      "timeslot": "02:00:00"
    },
    {
      "artist": "FOREVR",
      "song": "Columbus",
      "label": "Independent",
      "timeslot": "02:00:00"
    },
    {
      "artist": "ODETTE",
      "song": "Watch Me Read You",
      "label": "EMI",
      "timeslot": "02:30:00"
    },
    {
      "artist": "DAN SULTAN",
      "song": "Killer (Live)",
      "label": "Mushroom",
      "timeslot": "02:30:00"
    },
    {
      "artist": "THE CREASES",
      "song": "Is It Love",
      "label": "Cooking Vinyl",
      "timeslot": "02:30:00"
    },
    {
      "artist": "GRIZZLY BEAR",
      "song": "Mourning Sound",
      "label": "Sony",
      "timeslot": "02:30:00"
    }
  ]
}