{
  "title": "Monday night 4 October 2021 on ABC 1",
  "special": "The VAULT",
  "timeslot": "night",
  "date": "2021-10-04",
  "url": "https://www.abc.net.au/rage/playlist/monday-night-4-october-2021-on-abc-1/13567216",
  "tracks": [
    {
      "artist": "KIM CARNES",
      "song": "Does It Make You Remember",
      "label": "EMI America",
      "timeslot": "02:00:00"
    },
    {
      "artist": "F R DAVID",
      "song": "Words",
      "label": null,
      "timeslot": "02:00:00"
    },
    {
      "artist": "BARRY MANILOW",
      "song": "I Wanna Do It With You",
      "label": "Arista",
      "timeslot": "02:30:00"
    },
    {
      "artist": "BILLY JOEL",
      "song": "Allentown",
      "label": "Sony",
      "timeslot": "02:30:00"
    },
    {
      "artist": "STEPHEN CUMMINGS",
      "song": "We All Make Mistakes",
      "label": "Regular Records",
      "timeslot": "02:30:00"
    },
    {
      "artist": "DIVINYLS",
      "song": "Science Fiction",
      "label": "Virgin",
      "timeslot": "02:30:00"
    },
    {
      "artist": "FLASH & THE PAN",
      "song": "Waiting For A Train",
      "label": "Albert Productions",
      "timeslot": "02:30:00"
    },
    {
      "artist": "JO JO ZEP",
      "song": "Walk On By",
      "label": "EMI",
      "timeslot": "02:30:00"
    },
    {
      "artist": "EUROGLIDERS",
      "song": "No Laughing Matter",
      "label": "Mercury",
      "timeslot": "02:30:00"
    },
    {
      "artist": "KATE BUSH",
      "song": "Suspended In Gaffa",
      "label": "EMI",
      "timeslot": "02:30:00"
    },
    {
      "artist": "BLANCMANGE",
      "song": "Living On The Ceiling",
      "label": "Universal",
      "timeslot": "02:30:00"
    },
    {
      "artist": "SPANDAU BALLET",
      "song": "Lifeline",
      "label": "Festival",
      "timeslot": "03:00:00"
    },
    {
      "artist": "EURYTHMICS",
      "song": "Love Is A Stranger",
      "label": "BMG",
      "timeslot": "03:00:00"
    },
    {
      "artist": "ABBA",
      "song": "Under Attack",
      "label": "RCA Victor",
      "timeslot": "03:00:00"
    },
    {
      "artist": "KIM WILDE",
      "song": "Child Come Away",
      "label": "RAK",
      "timeslot": "03:00:00"
    },
    {
      "artist": "BUCKS FIZZ",
      "song": "If You Can't Stand The Heat",
      "label": "RCA Victor",
      "timeslot": "03:00:00"
    },
    {
      "artist": "WHAM",
      "song": "Young Guns (Go For It)",
      "label": "Sony",
      "timeslot": "03:00:00"
    },
    {
      "artist": "BILLY IDOL",
      "song": "White Wedding",
      "label": "Fest/Mush",
      "timeslot": "03:00:00"
    },
    {
      "artist": "THOMAS DOLBY",
      "song": "She Blinded Me With Science",
      "label": "EMI",
      "timeslot": "03:00:00"
    },
    {
      "artist": "MARVIN GAYE",
      "song": "Sexual Healing",
      "label": "Sony",
      "timeslot": "03:30:00"
    },
    {
      "artist": "HOT CHOCOLATE",
      "song": "Chances",
      "label": "RAK",
      "timeslot": "03:30:00"
    },
    {
      "artist": "THE POLICE",
      "song": "Roxanne",
      "label": "Polydor",
      "timeslot": "03:30:00"
    },
    {
      "artist": "MADNESS",
      "song": "Our House",
      "label": "Virgin",
      "timeslot": "03:30:00"
    },
    {
      "artist": "ZAINE GRIFF",
      "song": "Figures",
      "label": "Polydor",
      "timeslot": "03:30:00"
    },
    {
      "artist": "ULTRAVOX",
      "song": "Reap The Wild Wind",
      "label": "Festival Records",
      "timeslot": "03:30:00"
    },
    {
      "artist": "KISSING THE PINK",
      "song": "Watching Their Eyes",
      "label": "Independent",
      "timeslot": "03:30:00"
    },
    {
      "artist": "BAUHAUS",
      "song": "Ziggy Stardust",
      "label": "BMG",
      "timeslot": "03:30:00"
    },
    {
      "artist": "THE MONITORS",
      "song": "Having You Around Me",
      "label": null,
      "timeslot": "03:30:00"
    },
    {
      "artist": "DENNIS WATERMAN",
      "song": "I Could Be So Good For You",
      "label": "EMI",
      "timeslot": "04:00:00"
    },
    {
      "artist": "THE J. GEILS BAND",
      "song": "I Do",
      "label": "EMI",
      "timeslot": "04:00:00"
    },
    {
      "artist": "PETER FRAMPTON",
      "song": "Back To Eden",
      "label": "A & M Records",
      "timeslot": "04:00:00"
    },
    {
      "artist": "SAGA",
      "song": "On The Loose",
      "label": "Portrait",
      "timeslot": "04:00:00"
    },
    {
      "artist": "CHRIS DE BURGH",
      "song": "Don't Pay The Ferryman",
      "label": "Festival",
      "timeslot": "04:00:00"
    },
    {
      "artist": "STEEL BREEZE",
      "song": "You Don't Want Me Anymore",
      "label": null,
      "timeslot": "04:00:00"
    }
  ]
}