{
  "title": "Sunday night 7 March 2021 on ABC 1",
  "special": "New Music Videos",
  "timeslot": "night",
  "date": "2021-03-07",
  "url": "https://www.abc.net.au/rage/playlist/sunday-night-7-march-2021-on-abc-1/13222068",
  "tracks": [
    {
      "artist": "ST. VINCENT",
      "song": "Pay Your Way In Pain",
      "label": "Loma Vista",
      "timeslot": "01:00:00"
    },
    {
      "artist": "DMA'S",
      "song": "Appointment",
      "label": "I OH YOU",
      "timeslot": "01:00:00"
    },
    {
      "artist": "MANSIONAIR",
      "song": "More",
      "label": "Liberation",
      "timeslot": "01:00:00"
    },
    {
      "artist": "SHANNEN JAMES",
      "song": "Superstitious",
      "label": "Ivy League",
      "timeslot": "01:00:00"
    },
    {
      "artist": "JUAN WAUTERS ft. MAC DEMARCO",
      "song": "Real",
      "label": "Captured Tracks",
      "timeslot": "01:30:00"
    },
    {
      "artist": "REAL ESTATE",
      "song": "Half A Human",
      "label": "Domino",
      "timeslot": "01:30:00"
    },
    {
      "artist": "PEEL",
      "song": "Dyna",
      "label": "Third Eye Stimuli",
      "timeslot": "01:30:00"
    },
    {
      "artist": "MR. TEENAGE",
      "song": "Automatic Love",
      "label": "Independent",
      "timeslot": "01:30:00"
    },
    {
      "artist": "VIOLENT SOHO",
      "song": "Canada",
      "label": "I OH YOU",
      "timeslot": "01:30:00"
    },
    {
      "artist": "THE LAZY EYES",
      "song": "Where's My Brain??",
      "label": "Independent",
      "timeslot": "01:30:00"
    },
    {
      "artist": "WOLF ALICE",
      "song": "The Last Man On Earth",
      "label": "Liberator",
      "timeslot": "01:30:00"
    },
    {
      "artist": "DREGG",
      "song": "Evolve",
      "label": "Epitaph",
      "timeslot": "02:00:00"
    },
    {
      "artist": "VOID OF VISION ft. ECCA VANDAL",
      "song": "Decay",
      "label": "UNFD",
      "timeslot": "02:00:00"
    },
    {
      "artist": "SHORT STACK",
      "song": "Burn You Down",
      "label": "UNFD",
      "timeslot": "02:00:00"
    },
    {
      "artist": "AFI",
      "song": "Looking Tragic",
      "label": "Rise Records",
      "timeslot": "02:00:00"
    },
    {
      "artist": "SYCCO",
      "song": "My Ways",
      "label": "Future Classic",
      "timeslot": "02:00:00"
    },
    {
      "artist": "GENESIS OWUSU",
      "song": "Gold Chains",
      "label": "Ourness",
      "timeslot": "02:00:00"
    },
    {
      "artist": "MAHALIA ft. RICO NASTY",
      "song": "Jealous",
      "label": "East West Records",
      "timeslot": "02:00:00"
    },
    {
      "artist": "$NOT ft. DENZEL CURRY",
      "song": "Sangria",
      "label": "300 Entertainment",
      "timeslot": "02:00:00"
    },
    {
      "artist": "SILVER SYNTHETIC",
      "song": "In The Beginning",
      "label": "Third Man Records",
      "timeslot": "02:00:00"
    },
    {
      "artist": "TEX CRICK",
      "song": "Peaches & Cream",
      "label": "Mac's Record Label",
      "timeslot": "02:30:00"
    },
    {
      "artist": "KHRUANGBIN",
      "song": "Dearest Alfred",
      "label": "Dead Oceans",
      "timeslot": "02:30:00"
    },
    {
      "artist": "MERK",
      "song": "Laps Around The Sun",
      "label": "Our Golden Friend",
      "timeslot": "02:30:00"
    },
    {
      "artist": "REPO MAN",
      "song": "Deep",
      "label": "Independent",
      "timeslot": "02:30:00"
    },
    {
      "artist": "SKEGSS",
      "song": "Valhalla",
      "label": "Caroline",
      "timeslot": "02:30:00"
    },
    {
      "artist": "CHILDREN COLLIDE",
      "song": "Trampoline",
      "label": "Spinning Top",
      "timeslot": "02:30:00"
    },
    {
      "artist": "LIL TJAY ft. 6LACK",
      "song": "Calling My Phone",
      "label": "Columbia",
      "timeslot": "02:30:00"
    },
    {
      "artist": "RUEL",
      "song": "distance",
      "label": "Sony",
      "timeslot": "02:30:00"
    },
    {
      "artist": "LIL YACHTY ft. OLIVER TREE",
      "song": "Asshole",
      "label": "Quality Control",
      "timeslot": "03:00:00"
    },
    {
      "artist": "KITO ft. CHANNEL TRES & VAN JESS",
      "song": "Recap",
      "label": "Astralwerks",
      "timeslot": "03:00:00"
    },
    {
      "artist": "KERO KERO BONITO",
      "song": "The Princess & the clock",
      "label": "Polyvinyl Records",
      "timeslot": "03:00:00"
    },
    {
      "artist": "MIA WRAY",
      "song": "Never Gonna Be The Same",
      "label": "Ivy League",
      "timeslot": "03:00:00"
    },
    {
      "artist": "SUMNER",
      "song": "Stranded",
      "label": "Lab78",
      "timeslot": "03:00:00"
    },
    {
      "artist": "BECCA HATCH ft. PLANET VEGETA",
      "song": "Please U",
      "label": "Forever Ever",
      "timeslot": "03:00:00"
    },
    {
      "artist": "CHET FAKER",
      "song": "Get High",
      "label": "BMG/Detail Records",
      "timeslot": "03:00:00"
    },
    {
      "artist": "ALLORA",
      "song": "What Planet",
      "label": "Independent",
      "timeslot": "03:00:00"
    },
    {
      "artist": "PIPIN",
      "song": "Tunnel Vision",
      "label": "Independent",
      "timeslot": "03:00:00"
    },
    {
      "artist": "MIDDLE KIDS",
      "song": "Questions",
      "label": "Independent",
      "timeslot": "03:30:00"
    },
    {
      "artist": "SECOND IDOL",
      "song": "White Noise",
      "label": "Independent",
      "timeslot": "03:30:00"
    },
    {
      "artist": "KINGSWOOD",
      "song": "You Make It So Easy",
      "label": "Independent",
      "timeslot": "03:30:00"
    },
    {
      "artist": "CHAI ft. RIC WILSON",
      "song": "Maybe Chocolate Chips",
      "label": "Sub Pop",
      "timeslot": "03:30:00"
    },
    {
      "artist": "HAYLEY MARY",
      "song": "Would You Throw A Diamond?",
      "label": "I OH YOU",
      "timeslot": "03:30:00"
    },
    {
      "artist": "ROLLING BLACKOUTS COASTAL FEVER",
      "song": "The Only One",
      "label": "Ivy League",
      "timeslot": "03:30:00"
    },
    {
      "artist": "PARIS TEXAS",
      "song": "Heavy Metal",
      "label": "Independent",
      "timeslot": "03:30:00"
    },
    {
      "artist": "POLISH CLUB",
      "song": "Stop For A Minute",
      "label": null,
      "timeslot": "03:30:00"
    }
  ]
}