{
  "title": "Saturday night 27th January 2018 on ABC",
  "special": "Retro Month: Week 4",
  "timeslot": "night",
  "date": "2018-01-27",
  "url": "https://www.abc.net.au/rage/playlist/saturday-night-27th-january-2018-on-abc/9637708",
  "tracks": [
    {
      "artist": "ROCK ARENA",
      "song": "June 14, 1983 (The Angels, Manfredd Mann & The Blues Band)",
      "label": "ABC",
      "timeslot": "23:30:00"
    },
    {
      "artist": "THE ANGELS - LIVE AT NARARA '83",
      "song": "Comin' Down",
      "label": "Shock",
      "timeslot": "01:00:00"
    },
    {
      "artist": "COUNTDOWN",
      "song": "November 23, 1986 (536: Australian Made Tour)",
      "label": "ABC",
      "timeslot": "01:00:00"
    },
    {
      "artist": "ROCK ARENA",
      "song": "April 8, 1985 (330)",
      "label": "ABC",
      "timeslot": "01:00:00"
    },
    {
      "artist": "COUNTDOWN",
      "song": "April 10, 1983 (366: Mark and Wendy from Globos)",
      "label": "ABC",
      "timeslot": "01:00:00"
    },
    {
      "artist": "THE GLOBOS",
      "song": "Tinteralla Di Luna",
      "label": "Fest/Mush",
      "timeslot": "01:00:00"
    },
    {
      "artist": "COUNTDOWN",
      "song": "October 14, 1984 (438: Los Trios Ringbarkus)",
      "label": "ABC",
      "timeslot": "01:00:00"
    },
    {
      "artist": "MARLON WILLIAMS",
      "song": "What's Chasing You",
      "label": "Caroline",
      "timeslot": "01:00:00"
    },
    {
      "artist": "BAKER BOY",
      "song": "Cloud 9",
      "label": "Independent",
      "timeslot": "01:00:00"
    },
    {
      "artist": "YOTHU YINDI",
      "song": "Treaty",
      "label": "Mushroom",
      "timeslot": "01:00:00"
    },
    {
      "artist": "WARUMPI BAND",
      "song": "My Island Home",
      "label": "Festival",
      "timeslot": "01:00:00"
    },
    {
      "artist": "BLACK EYED PEAS",
      "song": "Where Is The Love?",
      "label": "Universal",
      "timeslot": "01:00:00"
    },
    {
      "artist": "DRAKE",
      "song": "Hotline Bling",
      "label": "Universal",
      "timeslot": "01:00:00"
    },
    {
      "artist": "MICHAEL JACKSON",
      "song": "Black Or White",
      "label": "Sony",
      "timeslot": "01:00:00"
    },
    {
      "artist": "DJ KHALED ft. RIHANNA & BRYSON TILLER",
      "song": "Wild Thoughts (clean)",
      "label": "Sony",
      "timeslot": "05:30:00"
    },
    {
      "artist": "BRUNO MARS",
      "song": "24K Magic",
      "label": "Warner",
      "timeslot": "05:30:00"
    },
    {
      "artist": "OUTKAST",
      "song": "Hey Ya",
      "label": "BMG",
      "timeslot": "05:30:00"
    },
    {
      "artist": "50 CENT",
      "song": "In Da Club",
      "label": "Universal",
      "timeslot": "05:30:00"
    },
    {
      "artist": "BAKER BOY",
      "song": "Marryuna",
      "label": "Independent",
      "timeslot": "05:30:00"
    },
    {
      "artist": "WHAT SO NOT ft. DANIEL JOHNS",
      "song": "Be Ok Again",
      "label": "Sweat It Out",
      "timeslot": "06:00:00"
    },
    {
      "artist": "THE PRESETS",
      "song": "Do What You Want",
      "label": "EMI",
      "timeslot": "06:00:00"
    },
    {
      "artist": "DUCKWRTH",
      "song": "Michuul",
      "label": "Universal",
      "timeslot": "06:00:00"
    },
    {
      "artist": "EMINEM ft. BEYONCE",
      "song": "Walk On Water (censored)",
      "label": "Universal",
      "timeslot": "06:00:00"
    },
    {
      "artist": "RUN THE JEWELS",
      "song": "Call Ticketron (clean)",
      "label": "Sony",
      "timeslot": "06:00:00"
    },
    {
      "artist": "YOUNG FATHERS",
      "song": "In My View",
      "label": "Ninja Tune",
      "timeslot": "06:00:00"
    },
    {
      "artist": "FRANZ FERDINAND",
      "song": "Feel The Love Go",
      "label": "EMI",
      "timeslot": "06:00:00"
    },
    {
      "artist": "THE BABE RAINBOW",
      "song": "Monky Disco",
      "label": "Flightless",
      "timeslot": "06:00:00"
    },
    {
      "artist": "POND",
      "song": "Fire In The Water",
      "label": "Spinning Top",
      "timeslot": "06:30:00"
    },
    {
      "artist": "CUB SPORT",
      "song": "Good Guys Go",
      "label": "Network Music",
      "timeslot": "06:30:00"
    },
    {
      "artist": "VANCE JOY",
      "song": "We're Going Home",
      "label": "Liberation",
      "timeslot": "06:30:00"
    },
    {
      "artist": "U2",
      "song": "Get Out Of Your Own Way",
      "label": "Universal",
      "timeslot": "06:30:00"
    },
    {
      "artist": "JACK WHITE",
      "song": "Connected By Love",
      "label": "Sony",
      "timeslot": "06:30:00"
    },
    {
      "artist": "DENT MAY",
      "song": "90210",
      "label": "Paw Tracks",
      "timeslot": "06:30:00"
    },
    {
      "artist": "BECK",
      "song": "Fix Me",
      "label": "EMI",
      "timeslot": "06:30:00"
    }
  ]
}