{
  "title": "Friday night  Friday, 7 May",
  "special": null,
  "timeslot": "night",
  "date": "2010-05-07",
  "url": "http://www.abc.net.au/rage/archive/s2893055.htm",
  "tracks": [
    {
      "artist": "SIA",
      "song": "Clap Your Hands",
      "label": "Inertia",
      "timeslot": "12:10:00"
    },
    {
      "artist": "OPERATOR PLEASE",
      "song": "Back And Forth",
      "label": "EMI",
      "timeslot": "12:10:00"
    },
    {
      "artist": "FIRE! SANTA ROSA, FIRE!",
      "song": "Little Cowboys, Bad Hombres",
      "label": "Remote Control",
      "timeslot": "12:10:00"
    },
    {
      "artist": "BOY & BEAR",
      "song": "Rabbit Song",
      "label": "Universal",
      "timeslot": "12:10:00"
    },
    {
      "artist": "LCD SOUNDSYSTEM",
      "song": "Drunk Girls",
      "label": "EMI",
      "timeslot": "12:10:00"
    },
    {
      "artist": "KIDZ IN SPACE",
      "song": "Downtime",
      "label": "Universal",
      "timeslot": "12:10:00"
    },
    {
      "artist": "K-OS",
      "song": "4 3 2 1",
      "label": "Shock",
      "timeslot": "12:30:00"
    },
    {
      "artist": "THE BEAUTIFUL GIRLS featuring VIDA-SUNSHYNE",
      "song": "10:10",
      "label": "Independent",
      "timeslot": "12:30:00"
    },
    {
      "artist": "CALVIN HARRIS",
      "song": "You Used To Hold Me",
      "label": "Sony",
      "timeslot": "12:30:00"
    },
    {
      "artist": "YEASAYER",
      "song": "One",
      "label": "EMI",
      "timeslot": "12:30:00"
    },
    {
      "artist": "BERTIE BLACKMAN",
      "song": "Peek-A-Boo",
      "label": "Independent",
      "timeslot": "12:30:00"
    },
    {
      "artist": "LUKE STEELE",
      "song": "Accidents Happen",
      "label": "MGM",
      "timeslot": "12:30:00"
    },
    {
      "artist": "MIDNIGHT JUGGERNAUTS",
      "song": "Vital Signs",
      "label": "Independent",
      "timeslot": "12:30:00"
    },
    {
      "artist": "GO/NO-GO",
      "song": "Turnaround",
      "label": "Independent",
      "timeslot": "12:30:00"
    },
    {
      "artist": "THE SPIRITS",
      "song": "The Other Half",
      "label": "Independent",
      "timeslot": "01:00:00"
    },
    {
      "artist": "PROFESSOR GREEN featuring ED DREWETT",
      "song": "I Need You Tonight",
      "label": "EMI",
      "timeslot": "01:00:00"
    },
    {
      "artist": "M-PHAZES featuring MUPH N PLUTONIC & CANDICE MONI",
      "song": "Goodbye Gravity",
      "label": "Obese Records",
      "timeslot": "01:00:00"
    },
    {
      "artist": "BOTANICS",
      "song": "What The Deal Is",
      "label": "Independent",
      "timeslot": "01:00:00"
    },
    {
      "artist": "B(IF)TEK",
      "song": "We Think You're Dishy (Koshowko Remix)",
      "label": "Independent",
      "timeslot": "01:00:00"
    },
    {
      "artist": "DIE ROTEN PUNKTE",
      "song": "Ich Bin Nicht Ein Roboter (I Am A Lion)",
      "label": "Independent",
      "timeslot": "01:00:00"
    },
    {
      "artist": "HAR MAR SUPERSTAR",
      "song": "Tall Boy",
      "label": "Independent",
      "timeslot": "01:00:00"
    },
    {
      "artist": "KIDS OF 88",
      "song": "Ribbons Of Light",
      "label": "Sony",
      "timeslot": "01:00:00"
    },
    {
      "artist": "SLASH featuring ANDREW STOCKDALE",
      "song": "By The Sword",
      "label": "Sony",
      "timeslot": "01:00:00"
    },
    {
      "artist": "THE DEAD WEATHER",
      "song": "Die By The Drop",
      "label": "Warner",
      "timeslot": "01:30:00"
    },
    {
      "artist": "WOLFMOTHER",
      "song": "Far Away",
      "label": "Universal",
      "timeslot": "01:30:00"
    },
    {
      "artist": "THE BAKER SUITE",
      "song": "When Darkness Falls",
      "label": "Independent",
      "timeslot": "01:30:00"
    },
    {
      "artist": "THE BOAT PEOPLE",
      "song": "Soporific",
      "label": "Independent",
      "timeslot": "01:30:00"
    },
    {
      "artist": "LAST DINOSAURS",
      "song": "Honolulu",
      "label": "Universal",
      "timeslot": "01:30:00"
    },
    {
      "artist": "DOVES",
      "song": "Andalucia",
      "label": "EMI",
      "timeslot": "01:30:00"
    },
    {
      "artist": "TUNNG",
      "song": "Hustle",
      "label": "Inertia",
      "timeslot": "01:30:00"
    },
    {
      "artist": "CRAYON FIELDS",
      "song": "Graceless",
      "label": "Independent",
      "timeslot": "02:00:00"
    },
    {
      "artist": "GEMMA RAY",
      "song": "100 Mph (In 2nd Gear)",
      "label": "Inertia",
      "timeslot": "02:00:00"
    },
    {
      "artist": "BIFFY CLYRO",
      "song": "Many Of Horror",
      "label": "Warner",
      "timeslot": "02:00:00"
    },
    {
      "artist": "ERNEST ELLIS",
      "song": "Loveless",
      "label": "Universal",
      "timeslot": "02:00:00"
    },
    {
      "artist": "BIG SCARY",
      "song": "Falling Away",
      "label": "Independent",
      "timeslot": "02:00:00"
    },
    {
      "artist": "THE KISSAWAY TRAIL",
      "song": "SDP",
      "label": "Inertia",
      "timeslot": "02:00:00"
    },
    {
      "artist": "DAN PARSONS",
      "song": "Firestarter",
      "label": "Independent",
      "timeslot": "02:00:00"
    },
    {
      "artist": "MOTOCADE",
      "song": "Oldest Trick In The Book",
      "label": "Independent",
      "timeslot": "02:00:00"
    },
    {
      "artist": "CLOUD CONTROL",
      "song": "This Is What I Said",
      "label": "Ivy League",
      "timeslot": "02:30:00"
    },
    {
      "artist": "PRINCESS ONE POINT FIVE",
      "song": "Today",
      "label": "Independent",
      "timeslot": "02:30:00"
    },
    {
      "artist": "YOUNG SID featuring KAYO",
      "song": "Never Waste A Day",
      "label": "Universal",
      "timeslot": "02:30:00"
    },
    {
      "artist": "REFLECTION ETERNAL",
      "song": "In This World",
      "label": "Warner",
      "timeslot": "02:30:00"
    },
    {
      "artist": "SMILE ON IMPACT vs CAPTAINS",
      "song": "Man Outta Me",
      "label": "Independent",
      "timeslot": "02:30:00"
    },
    {
      "artist": "DECLAN AND THE ANTICS",
      "song": "Born For The Nightlife",
      "label": "Independent",
      "timeslot": "02:30:00"
    },
    {
      "artist": "WE HAVE BAND",
      "song": "Divisive",
      "label": "Inertia",
      "timeslot": "02:30:00"
    },
    {
      "artist": "FRENCH ROCKETS",
      "song": "1x1",
      "label": "Independent",
      "timeslot": "02:30:00"
    },
    {
      "artist": "ERYKAH BADU",
      "song": "Window Seat",
      "label": "Universal",
      "timeslot": "03:00:00"
    },
    {
      "artist": "ALBERTA CROSS",
      "song": "Old Man Chicago",
      "label": "Universal",
      "timeslot": "03:00:00"
    },
    {
      "artist": "BLACK REBEL MOTORCYLE CLUB",
      "song": "Beat The Devil's Tattoo",
      "label": "Shock",
      "timeslot": "03:00:00"
    },
    {
      "artist": "FREE ENERGY",
      "song": "Free Energy",
      "label": "EMI",
      "timeslot": "03:00:00"
    },
    {
      "artist": "AN HORSE",
      "song": "Postcards",
      "label": "Shock",
      "timeslot": "03:00:00"
    },
    {
      "artist": "DEFTONES",
      "song": "Diamond Eyes",
      "label": "Warner",
      "timeslot": "03:00:00"
    },
    {
      "artist": "HOWL",
      "song": "Anyone But Us",
      "label": "Shock",
      "timeslot": "03:00:00"
    },
    {
      "artist": "ESCAPE THE FATE",
      "song": "This War Is Ours",
      "label": "Shock",
      "timeslot": "03:00:00"
    },
    {
      "artist": "CANCER BATS",
      "song": "Sabotage",
      "label": "Independent",
      "timeslot": "03:30:00"
    },
    {
      "artist": "ARSIS",
      "song": "Forced To Rock",
      "label": "Riot",
      "timeslot": "03:30:00"
    },
    {
      "artist": "BULLET FOR MY VALENTINE",
      "song": "The Last Fight",
      "label": "Sony",
      "timeslot": "03:30:00"
    },
    {
      "artist": "OVERKILL",
      "song": "Bring Me The Night",
      "label": "Riot",
      "timeslot": "03:30:00"
    },
    {
      "artist": "EVERY TIME I DIE",
      "song": "After One Quarter Of A Revolution",
      "label": "Shock",
      "timeslot": "03:30:00"
    },
    {
      "artist": "INJURED NINJA",
      "song": "IDDQD",
      "label": "Independent",
      "timeslot": "03:30:00"
    },
    {
      "artist": "CITY OF FIRE",
      "song": "Rising",
      "label": "Stomp",
      "timeslot": "04:00:00"
    },
    {
      "artist": "THE CHURCH OF HYSTERIA",
      "song": "No",
      "label": "Independent",
      "timeslot": "04:00:00"
    },
    {
      "artist": "JAYDEN LOCASTRO",
      "song": "Shadows",
      "label": "Independent",
      "timeslot": "04:00:00"
    },
    {
      "artist": "TAYLAH LOCASTRO",
      "song": "Just Think About It",
      "label": "Independent",
      "timeslot": "04:00:00"
    },
    {
      "artist": "COOPERBLACK",
      "song": "Salted",
      "label": "Independent",
      "timeslot": "04:00:00"
    },
    {
      "artist": "MAD COWBOY DISEASE",
      "song": "Katoomba Street",
      "label": "Independent",
      "timeslot": "04:00:00"
    },
    {
      "artist": "TONY FAEHSE",
      "song": "Streets Of Paris",
      "label": "Independent",
      "timeslot": "04:00:00"
    },
    {
      "artist": "GRETCHEN LEWIS",
      "song": "Underground @ 30",
      "label": "Independent",
      "timeslot": "04:30:00"
    },
    {
      "artist": "THESE NEW PURITANS",
      "song": "Attack Music",
      "label": "EMI",
      "timeslot": "04:30:00"
    },
    {
      "artist": "MECK featuring DINO",
      "song": "Feels Like A Prayer",
      "label": "Warner",
      "timeslot": "04:30:00"
    },
    {
      "artist": "FAITHLESS",
      "song": "Not Going Home",
      "label": "Liberation",
      "timeslot": "04:30:00"
    },
    {
      "artist": "LIL WAYNE featuring EMINEM",
      "song": "Drop The Word",
      "label": "Universal",
      "timeslot": "04:30:00"
    },
    {
      "artist": "LMFAO featuring LIL JOHN",
      "song": "Shots",
      "label": "Universal",
      "timeslot": "04:30:00"
    },
    {
      "artist": "CHRISTINA AGUILERA",
      "song": "Not Myself Tonight",
      "label": "Sony",
      "timeslot": "04:30:00"
    },
    {
      "artist": "NICKY BOMBA",
      "song": "Rock Ya Mama",
      "label": "Independent",
      "timeslot": "04:30:00"
    },
    {
      "artist": "CASCADA",
      "song": "Pyromania",
      "label": "Universal",
      "timeslot": "05:00:00"
    },
    {
      "artist": "STROMAE",
      "song": "Alors On Dance",
      "label": "Universal",
      "timeslot": "05:00:00"
    },
    {
      "artist": "OU EST LE SWIMMING POOL",
      "song": "Dance The Way I Feel",
      "label": "Independent",
      "timeslot": "05:00:00"
    },
    {
      "artist": "SPACE INVADAS",
      "song": "Done It Again",
      "label": "Independent",
      "timeslot": "05:00:00"
    },
    {
      "artist": "LADY GAGA featuring BEYONCE",
      "song": "Telephone",
      "label": "Universal",
      "timeslot": "05:00:00"
    },
    {
      "artist": "RICHARD VISSION & STATIC REVENGER",
      "song": "I Like That",
      "label": "Vicious",
      "timeslot": "05:00:00"
    },
    {
      "artist": "DAVID GUETTA featuring KID CUDI",
      "song": "Memories",
      "label": "EMI",
      "timeslot": "05:00:00"
    },
    {
      "artist": "ALEXANDRA BURKE featuring PITBULL",
      "song": "All Night Long",
      "label": "Sony",
      "timeslot": "05:00:00"
    },
    {
      "artist": "FRANK TURNER",
      "song": "Isabel",
      "label": "Shock",
      "timeslot": "05:30:00"
    },
    {
      "artist": "ISRAEL CANNAN",
      "song": "One Fine Day",
      "label": "Independent",
      "timeslot": "05:30:00"
    },
    {
      "artist": "MARK SHOLTEZ",
      "song": "We Could Get Lost",
      "label": "Warner",
      "timeslot": "05:30:00"
    },
    {
      "artist": "MOJADA",
      "song": "Find A Way",
      "label": "Independent",
      "timeslot": "05:30:00"
    },
    {
      "artist": "LADY ANTEBELLUM",
      "song": "Need You Now",
      "label": "EMI",
      "timeslot": "05:30:00"
    },
    {
      "artist": "NORAH JONES",
      "song": "Young Blood",
      "label": "EMI",
      "timeslot": "05:30:00"
    },
    {
      "artist": "JANELLE MONAE featuring BIG BOI",
      "song": "Tightrope",
      "label": "Warner",
      "timeslot": "05:30:00"
    }
  ]
}