{
  "title": "Monday night 18 February 2019 on ABC",
  "special": "The VAULT: Oz Pop and Rock 1990",
  "timeslot": "night",
  "date": "2019-02-18",
  "url": "https://www.abc.net.au/rage/playlist/monday-night-18-february-2019-on-abc/10822682",
  "tracks": [
    {
      "artist": "MIDNIGHT OIL",
      "song": "Blue Sky Mine",
      "label": "Sony",
      "timeslot": "01:00:00"
    },
    {
      "artist": "HUNTERS & COLLECTORS",
      "song": "Turn A Blind Eye",
      "label": "Mushroom",
      "timeslot": "01:30:00"
    },
    {
      "artist": "THE BLACK SORROWS",
      "song": "Harley _and_ Rose",
      "label": "CBS",
      "timeslot": "01:30:00"
    },
    {
      "artist": "SHANE HOWARD",
      "song": "Walk On Fire",
      "label": "RCA Victor",
      "timeslot": "01:30:00"
    },
    {
      "artist": "CROWDED HOUSE",
      "song": "I Feel Possessed",
      "label": "Capitol",
      "timeslot": "01:30:00"
    },
    {
      "artist": "BOOM CRASH OPERA",
      "song": "Dancing In The Storm",
      "label": "WEA",
      "timeslot": "01:30:00"
    },
    {
      "artist": "ABSENT FRIENDS",
      "song": "Harmony",
      "label": null,
      "timeslot": "01:30:00"
    },
    {
      "artist": "ABSENT FRIENDS ft. WENDY MATTHEWS",
      "song": "Nobody But You",
      "label": "Phonogram",
      "timeslot": "01:30:00"
    },
    {
      "artist": "WENDY MATTHEWS",
      "song": "Token Angels",
      "label": "rooART",
      "timeslot": "02:00:00"
    },
    {
      "artist": "THE CHURCH",
      "song": "You're Still Beautiful",
      "label": "Mushroom",
      "timeslot": "02:00:00"
    },
    {
      "artist": "THE CHURCH",
      "song": "Metropolis",
      "label": "Mushroom",
      "timeslot": "02:00:00"
    },
    {
      "artist": "RATCAT",
      "song": "That Ain't Bad",
      "label": "Polydor",
      "timeslot": "02:00:00"
    },
    {
      "artist": "THE FALLING JOYS",
      "song": "Lock It",
      "label": "BMG",
      "timeslot": "02:00:00"
    },
    {
      "artist": "THE HUMMINGBIRDS",
      "song": "Alimony",
      "label": "Phantom Records",
      "timeslot": "02:00:00"
    }
  ]
}