{
  "title": "Saturday morning 2nd December 2017 on ABC",
  "special": null,
  "timeslot": "morning",
  "date": "2017-12-02",
  "url": "https://www.abc.net.au/rage/playlist/saturday-morning-2nd-december-2017-on-abc/9645178",
  "tracks": [
    {
      "artist": "CALVIN HARRIS ft. KEHLANI & LIL YACHTY",
      "song": "Faking It (clean)",
      "label": "Sony",
      "timeslot": "06:00:00"
    },
    {
      "artist": "LUIS FONSI & DEMI LOVATO",
      "song": "Echame La Culpa",
      "label": "Universal",
      "timeslot": "06:00:00"
    },
    {
      "artist": "SIA",
      "song": "Santa's Coming For Us",
      "label": "Atlantic",
      "timeslot": "06:00:00"
    },
    {
      "artist": "MARIAH CAREY",
      "song": "The Star",
      "label": "Sony",
      "timeslot": "06:00:00"
    },
    {
      "artist": "LAUV",
      "song": "Paris In The Rain",
      "label": "Kobalt",
      "timeslot": "06:00:00"
    },
    {
      "artist": "TAYLOR SWIFT",
      "song": "...Ready For It? (censored)",
      "label": "Universal",
      "timeslot": "06:00:00"
    },
    {
      "artist": "DEMI LOVATO",
      "song": "Sorry Not Sorry (Clean)",
      "label": "Universal",
      "timeslot": "06:00:00"
    },
    {
      "artist": "PINK",
      "song": "What About Us",
      "label": "Sony",
      "timeslot": "06:00:00"
    },
    {
      "artist": "RITA ORA",
      "song": "Anywhere",
      "label": "Warner",
      "timeslot": "06:30:00"
    },
    {
      "artist": "IMAGINE DRAGONS",
      "song": "Thunder",
      "label": "Universal",
      "timeslot": "06:30:00"
    },
    {
      "artist": "LAUV",
      "song": "I Like Me Better",
      "label": "Kobalt",
      "timeslot": "06:30:00"
    },
    {
      "artist": "MACKLEMORE ft. SKYLAR GREY",
      "song": "Glorious",
      "label": "Warner",
      "timeslot": "06:30:00"
    },
    {
      "artist": "CHARLIE PUTH",
      "song": "How Long",
      "label": "Warner",
      "timeslot": "06:30:00"
    },
    {
      "artist": "LOGIC ft. ALESSIA CARA & KHALID",
      "song": "1-800-273-8255 (CENSORED)",
      "label": "Universal",
      "timeslot": "06:30:00"
    },
    {
      "artist": "HAILEE STEINFELD & ALESSO",
      "song": "Let Me Go ft. FLORIDA GEORGIA & WATT",
      "label": "Universal",
      "timeslot": "06:30:00"
    },
    {
      "artist": "PORTUGAL. THE MAN",
      "song": "Feel It Still",
      "label": "Atlantic",
      "timeslot": "06:30:00"
    },
    {
      "artist": "ZAYN ft. SIA",
      "song": "Dusk Til Dawn",
      "label": "Sony",
      "timeslot": "07:00:00"
    },
    {
      "artist": "MACKLEMORE ft. KESHA",
      "song": "Good Old Days",
      "label": "Warner",
      "timeslot": "07:00:00"
    },
    {
      "artist": "DUA LIPA",
      "song": "New Rules",
      "label": "Warner",
      "timeslot": "07:00:00"
    },
    {
      "artist": "MAROON 5 ft. SZA",
      "song": "What Lovers Do",
      "label": "Universal",
      "timeslot": "07:00:00"
    },
    {
      "artist": "SAM SMITH",
      "song": "Too Good At Goodbyes",
      "label": "Capital Records",
      "timeslot": "07:00:00"
    },
    {
      "artist": "KHALID",
      "song": "Young, Dumb & Broke",
      "label": "Sony",
      "timeslot": "07:00:00"
    },
    {
      "artist": "MARSHMELLO & KHALID",
      "song": "Silence",
      "label": "RCA",
      "timeslot": "07:00:00"
    },
    {
      "artist": "SELENA GOMEZ & MARSHMELLO",
      "song": "Wolves",
      "label": "Universal",
      "timeslot": "07:00:00"
    },
    {
      "artist": "ED SHEERAN",
      "song": "Perfect",
      "label": "Warner",
      "timeslot": "07:30:00"
    },
    {
      "artist": "MACHINE GUN KELLY, X AMBASSADORS & BEBE REXHA",
      "song": "Home",
      "label": "Warner",
      "timeslot": "07:30:00"
    },
    {
      "artist": "CAMILLA CABELLO ft. YOUNG THUG",
      "song": "Havana",
      "label": "Sony",
      "timeslot": "07:30:00"
    },
    {
      "artist": "BJORK",
      "song": "Blissing Me",
      "label": "Pod",
      "timeslot": "07:30:00"
    },
    {
      "artist": "ANATOLE ft. TOM IANSEK",
      "song": "Outgrown",
      "label": "Good Manners",
      "timeslot": "07:30:00"
    },
    {
      "artist": "MARLON WILLIAMS & ALDOUS HARDING",
      "song": "Nobody Gets What They Want Anymore",
      "label": "Caroline",
      "timeslot": "07:30:00"
    },
    {
      "artist": "SLUM SOCIABLE",
      "song": "Keep Up With It",
      "label": "Liberation",
      "timeslot": "08:00:00"
    },
    {
      "artist": "QUEENS OF THE STONE AGE",
      "song": "The Way You Used To Do",
      "label": "Matador Records",
      "timeslot": "08:00:00"
    },
    {
      "artist": "KING GIZZARD & THE LIZARD WIZARD",
      "song": "Let There Be Rock (live)",
      "label": null,
      "timeslot": "08:00:00"
    },
    {
      "artist": "PEKING DUCK ft. ICONA POP",
      "song": "Let You Down (clean)",
      "label": "Sony",
      "timeslot": "08:00:00"
    },
    {
      "artist": "EMPIRE OF THE SUN",
      "song": "On Our Way Home",
      "label": "EMI",
      "timeslot": "08:00:00"
    },
    {
      "artist": "JOHN MAUS",
      "song": "Touchdown",
      "label": "Domino",
      "timeslot": "08:00:00"
    },
    {
      "artist": "IVAN OOZE ft. GHOSTFACE KILLAH",
      "song": "Bills (censored version)",
      "label": "Independent",
      "timeslot": "08:30:00"
    },
    {
      "artist": "GORILLAZ",
      "song": "Rock The House",
      "label": "EMI",
      "timeslot": "08:30:00"
    },
    {
      "artist": "RAGE AGAINST THE MACHINE",
      "song": "Guerilla Radio",
      "label": "Sony",
      "timeslot": "08:30:00"
    },
    {
      "artist": "JIMI HENDRIX",
      "song": "Hear My Train A Comin'",
      "label": "Polydor",
      "timeslot": "08:30:00"
    },
    {
      "artist": "THE DOORS - LIVE",
      "song": "Love Me Two Times",
      "label": "Warner",
      "timeslot": "08:30:00"
    },
    {
      "artist": "BUSTA RHYMES",
      "song": "Woo-Hah!! (Got You All In Check)",
      "label": "Warner",
      "timeslot": "08:30:00"
    },
    {
      "artist": "KORN",
      "song": "Freak On A Leash",
      "label": "Sony",
      "timeslot": "08:30:00"
    },
    {
      "artist": "FATBOY SLIM",
      "song": "Weapon Of Choice",
      "label": "Sony",
      "timeslot": "09:00:00"
    },
    {
      "artist": "MICHAEL JACKSON",
      "song": "The Way You Make Me Feel",
      "label": "Sony",
      "timeslot": "09:00:00"
    },
    {
      "artist": "IVAN OOZE",
      "song": "Get With It",
      "label": "Independent",
      "timeslot": "09:00:00"
    },
    {
      "artist": "YUNGBLUD",
      "song": "I Love You Will You Marry Me",
      "label": "Universal",
      "timeslot": "09:00:00"
    },
    {
      "artist": "TOTALLY MILD",
      "song": "Today Tonight",
      "label": "Our Golden Friend",
      "timeslot": "09:00:00"
    },
    {
      "artist": "ASHA JEFFERIES",
      "song": "Coburg",
      "label": "Independent",
      "timeslot": "09:00:00"
    },
    {
      "artist": "PHANOSLAND",
      "song": "Aphrodite's New Order",
      "label": "Dinosaur City",
      "timeslot": "09:30:00"
    },
    {
      "artist": "AIRWOLF ft. SOPHIEGROPHY",
      "song": "Blazin",
      "label": "Etc Etc",
      "timeslot": "09:30:00"
    },
    {
      "artist": "VERA BLUE",
      "song": "Regular Touch",
      "label": "Universal",
      "timeslot": "09:30:00"
    },
    {
      "artist": "FLIGHT FACILITIES ft. BROODS, REGGIE WATTS & SAR",
      "song": "Stranded",
      "label": "Future Classic",
      "timeslot": "09:30:00"
    },
    {
      "artist": "KIMBRA",
      "song": "Top Of The World",
      "label": "Warner",
      "timeslot": "09:30:00"
    },
    {
      "artist": "OK GO",
      "song": "Obsession",
      "label": "Paracadute",
      "timeslot": "09:30:00"
    },
    {
      "artist": "TINY LITTLE HOUSES",
      "song": "Entitled Generation",
      "label": "Ivy League",
      "timeslot": "09:30:00"
    },
    {
      "artist": "HOCKEY DAD",
      "song": "Homely Feeling",
      "label": "Farmer & The Owl / Inertia",
      "timeslot": "09:30:00"
    },
    {
      "artist": "DARYL BRAITHWAITE",
      "song": "The Horses",
      "label": "Sony",
      "timeslot": "10:00:00"
    },
    {
      "artist": "MIDNIGHT OIL",
      "song": "Forgotten Years",
      "label": "Sony",
      "timeslot": "10:00:00"
    },
    {
      "artist": "ALEX LAHEY",
      "song": "You Don't Think You Like People Like Me",
      "label": "Independent",
      "timeslot": "10:00:00"
    },
    {
      "artist": "FOO FIGHTERS",
      "song": "Learn To Fly",
      "label": "BMG",
      "timeslot": "10:00:00"
    },
    {
      "artist": "THE PREATURES",
      "song": "Is This How You Feel?",
      "label": "Universal",
      "timeslot": "10:00:00"
    },
    {
      "artist": "SNEAKY SOUND SYSTEM",
      "song": "Pictures",
      "label": "MGM",
      "timeslot": "10:00:00"
    },
    {
      "artist": "CLIENT LIAISON",
      "song": "Off White Limousine (Censored Version)",
      "label": "Remote Control",
      "timeslot": "10:00:00"
    },
    {
      "artist": "SAM SMITH",
      "song": "Stay With Me",
      "label": "EMI",
      "timeslot": "10:00:00"
    },
    {
      "artist": "COLDPLAY",
      "song": "Viva La Vida",
      "label": "EMI",
      "timeslot": "10:30:00"
    },
    {
      "artist": "AUSTRALIAN CRAWL",
      "song": "Reckless",
      "label": "EMI",
      "timeslot": "10:30:00"
    },
    {
      "artist": "ABBA",
      "song": "Knowing Me, Knowing You",
      "label": "Mercury",
      "timeslot": "10:30:00"
    },
    {
      "artist": "THE CHURCH",
      "song": "Under The Milky Way",
      "label": "Mushroom",
      "timeslot": "10:30:00"
    },
    {
      "artist": "COLD CHISEL",
      "song": "Flame Trees",
      "label": "Warner",
      "timeslot": "10:30:00"
    },
    {
      "artist": "DARYL BRAITHWAITE",
      "song": "As The Days Go By",
      "label": "CBS",
      "timeslot": "10:30:00"
    }
  ]
}