{
  "title": "Tuesday night 26 March 2019 on ABC ME",
  "special": null,
  "timeslot": "night",
  "date": "2019-03-26",
  "url": "https://www.abc.net.au/rage/playlist/tuesday-night-26-march-2019-on-abc-me/10942396",
  "tracks": [
    {
      "artist": "BEHEMOTH",
      "song": "Ben Sahar (censored)",
      "label": "Nuclear Blast",
      "timeslot": "21:00:00"
    },
    {
      "artist": "ME AND THAT MAN",
      "song": "Ain't Much Loving",
      "label": "Cooking Vinyl",
      "timeslot": "21:30:00"
    },
    {
      "artist": "MORRISSEY",
      "song": "Spent The Day In Bed",
      "label": "BMG",
      "timeslot": "21:30:00"
    },
    {
      "artist": "AMY WINEHOUSE",
      "song": "Back To Black",
      "label": "Universal",
      "timeslot": "21:30:00"
    },
    {
      "artist": "BECK",
      "song": "Loser",
      "label": "Universal (MCA)",
      "timeslot": "21:30:00"
    },
    {
      "artist": "DIRE STRAITS",
      "song": "Money For Nothing",
      "label": "Polydor",
      "timeslot": "21:30:00"
    },
    {
      "artist": "AC/DC",
      "song": "It's A Long Way To The Top",
      "label": "EMI",
      "timeslot": "21:30:00"
    },
    {
      "artist": "IGGY POP",
      "song": "Lust For Life",
      "label": "Virgin",
      "timeslot": "22:00:00"
    },
    {
      "artist": "FAITH NO MORE",
      "song": "Epic",
      "label": "Festival",
      "timeslot": "22:00:00"
    },
    {
      "artist": "AFI",
      "song": "Miss Murder",
      "label": "Universal",
      "timeslot": "22:00:00"
    },
    {
      "artist": "GARY NUMAN",
      "song": "Love Hurt Bleed",
      "label": "Warp",
      "timeslot": "22:00:00"
    },
    {
      "artist": "DURAN DURAN",
      "song": "Save A Prayer",
      "label": "EMI",
      "timeslot": "22:00:00"
    },
    {
      "artist": "ALPHAVILLE",
      "song": "Forever Young",
      "label": "Warner",
      "timeslot": "22:00:00"
    }
  ]
}